notacheat/__init__.py
notacheat/__version__.py
notacheat/notacheat.py
notacheat-0.2.5.dist-info/METADATA
notacheat-0.2.5.dist-info/WHEEL
notacheat-0.2.5.dist-info/top_level.txt
notacheat-0.2.5.dist-info/RECORD
