Metadata-Version: 2.1
Name: notacheat
Version: 0.2.5
Summary: A package made so that all hischoolers can use.
Home-page: http://github.com/P-Minjae
Author: Minjae Park 25-21208
Author-email: minjaepark3837@gmail.com
Classifier: Programming Language :: Python :: 3
Classifier: License :: OSI Approved :: MIT License
Classifier: Operating System :: OS Independent
Requires-Python: >=3.6
